{
    "DNDConfig": null,
    "__parentReadjusting__": false,
    "_height_": {
        "type": "string",
        "value": "20dp"
    },
    "_left_": {
        "type": "string",
        "value": "3%"
    },
    "_margin_": [
        0,
        0,
        0,
        0
    ],
    "_orientation_": 6,
    "_padding_": [
        0,
        0,
        0,
        0
    ],
    "_percent_": true,
    "_skin_": "sd1421164da64fc0aea0355e19e3a7a4",
    "_top_": {
        "type": "string",
        "value": "35%"
    },
    "_width_": {
        "type": "string",
        "value": "20dp"
    },
    "allboxes": [],
    "autogrowmode": 0,
    "canUpdateUI": true,
    "children": [
        "ImgDel"
    ],
    "clipbounds": true,
    "containerId": true,
    "containerweight": 100,
    "desktopweb": {
        "psp": {}
    },
    "enablescrolling": true,
    "id": "flexDel",
    "ide_onClick": "AS_FlexContainer_gbc0a1a83c6f457498c362d7ecb36483",
    "info": null,
    "iscustomlayout": false,
    "isvisible": true,
    "kuid": "ee5b40715cb0484facdda84bdcd39fd0",
    "layouttype": 2,
    "name": "kony.ui.FlexContainer",
    "onclick": "AS_FlexContainer_gbc0a1a83c6f457498c362d7ecb36483",
    "parent": "flexAddAndDel",
    "pf": "tempSpeaker",
    "retaincontentalignment": false,
    "retainflexpositionproperties": false,
    "snapgridsize": 10,
    "snaptogrid": true,
    "wType": "FlexContainer",
    "widgetalignment": 1,
    "zindex": 1
}